Metadata-Version: 2.1
Name: bisheng-pyautogen
Version: 0.3.2
Summary: Enabling Next-Gen LLM Applications via Multi-Agent Conversation Framework
Home-page: https://github.com/microsoft/autogen
Author: AutoGen
Author-email: auto-gen@outlook.com
Classifier: Programming Language :: Python :: 3
Classifier: License :: OSI Approved :: MIT License
Classifier: Operating System :: OS Independent
Requires-Python: >=3.8
License-File: LICENSE
License-File: LICENSE-CODE
Requires-Dist: openai (>1)
Requires-Dist: diskcache
Requires-Dist: termcolor
Requires-Dist: flaml
Requires-Dist: python-dotenv
Provides-Extra: blendsearch
Requires-Dist: flaml[blendsearch] ; extra == 'blendsearch'
Provides-Extra: mathchat
Requires-Dist: sympy ; extra == 'mathchat'
Requires-Dist: pydantic (==1.10.9) ; extra == 'mathchat'
Requires-Dist: wolframalpha ; extra == 'mathchat'
Provides-Extra: retrievechat
Requires-Dist: chromadb ; extra == 'retrievechat'
Requires-Dist: tiktoken ; extra == 'retrievechat'
Requires-Dist: sentence-transformers ; extra == 'retrievechat'
Requires-Dist: pypdf ; extra == 'retrievechat'
Provides-Extra: teachable
Requires-Dist: chromadb ; extra == 'teachable'
Provides-Extra: test
Requires-Dist: chromadb ; extra == 'test'
Requires-Dist: lancedb ; extra == 'test'
Requires-Dist: coverage (>=5.3) ; extra == 'test'
Requires-Dist: datasets ; extra == 'test'
Requires-Dist: ipykernel ; extra == 'test'
Requires-Dist: nbconvert ; extra == 'test'
Requires-Dist: nbformat ; extra == 'test'
Requires-Dist: pre-commit ; extra == 'test'
Requires-Dist: pydantic (==1.10.9) ; extra == 'test'
Requires-Dist: pytest-asyncio ; extra == 'test'
Requires-Dist: pytest (>=6.1.1) ; extra == 'test'
Requires-Dist: sympy ; extra == 'test'
Requires-Dist: tiktoken ; extra == 'test'
Requires-Dist: wolframalpha ; extra == 'test'
Requires-Dist: qdrant-client[fastembed] ; extra == 'test'
Requires-Dist: langchain ; extra == 'test'
